{
  "schema_version": 1,
  "raw_basename": "thermal_2026-04-05_14-55-31.raw",
  "source": "thermal_web_app",
  "capture": {
    "duration": 120.0,
    "refresh_rate": 32,
    "capture_fps": 16,
    "output_dir": "/home/metabowlite/IR_Mblite/output/session_2026-03-29_15-23-38"
  },
  "estimate": {
    "water_volume": 1000.0,
    "calibration": true,
    "urine_volume": 500.0,
    "urine_temp": 43.0,
    "segment_teq_window_s": 10.0,
    "patches_teq_window_s": 10.0,
    "segment_water_temp_mode": "min",
    "patches_water_temp_mode": "min",
    "segment_teq_temp_mode": "average",
    "patches_teq_temp_mode": "max",
    "segment_fps_for_calculation": 4.0,
    "patches_fps_for_calculation": 4.0,
    "temp_method": "both",
    "segment_retain_fraction": 0.7,
    "segment_min_delta_c": 1.0
  },
  "estimate_result": {
    "segment_water_volume_ml": 1347.0118241756766,
    "patches_water_volume_ml": 1564.3970087600846
  },
  "user_form": {
    "enabled": true,
    "event": "Pee",
    "poop_amount": null,
    "poop_type": null,
    "pee_type": "No Foam",
    "toilet_paper_amount": "None",
    "submitted_at": "2026-04-05T14:58:04"
  }
}
